.gitignore
README.rst
bootstrap.py
buildout.cfg
setup.py
collective/__init__.py
collective.picnik.egg-info/PKG-INFO
collective.picnik.egg-info/SOURCES.txt
collective.picnik.egg-info/dependency_links.txt
collective.picnik.egg-info/entry_points.txt
collective.picnik.egg-info/namespace_packages.txt
collective.picnik.egg-info/not-zip-safe
collective.picnik.egg-info/requires.txt
collective.picnik.egg-info/top_level.txt
collective/picnik/__init__.py
collective/picnik/config.py
collective/picnik/configure.zcml
collective/picnik/controlpanel.py
collective/picnik/edit.py
collective/picnik/handle_pull.py
collective/picnik/interfaces.py
collective/picnik/picnik.png
collective/picnik/rebuild_i18n.sh
collective/picnik/upgrades.py
collective/picnik/upgrades.zcml
collective/picnik/locales/collective.picnik.pot
collective/picnik/locales/fr/LC_MESSAGES/collective.picnik.po
collective/picnik/profiles/default/actions.xml
collective/picnik/profiles/default/browserlayer.xml
collective/picnik/profiles/default/controlpanel.xml
collective/picnik/profiles/default/metadata.xml
collective/picnik/profiles/default/registry.xml
collective/picnik/tests/__init__.py
collective/picnik/tests/base.py
collective/picnik/tests/layer.py
collective/picnik/tests/test_edit.py
collective/picnik/tests/test_handle_pull.py
collective/picnik/tests/utils.py
docs/HISTORY.txt
docs/INSTALL.txt
docs/LICENSE.GPL
docs/LICENSE.txt