Metadata-Version: 1.0
Name: collective.picnik
Version: 1.1
Summary: Integration of picnik service into Plone
Home-page: http://toutpt.makina-corpus.org/en/add-ons/collective.picnik
Author: JeanMichel FRANCOIS aka toutpt
Author-email: toutpt@gmail.com
License: GPL
Platform: UNKNOWN
Classifier: Framework :: Plone
Classifier: Programming Language :: Python
